gcviz/__init__.py
gcviz/__main__.py
gcviz/app.py
gcviz/components.py
gcviz/compounds.py
gcviz/config.py
gcviz/defaults.py
gcviz/fit.py
gcviz/flags.py
gcviz/netcdf.py
gcviz/stats.py
gcviz/style.py
gcviz/utils.py
gcviz/view.py
gcviz/layout/__init__.py
gcviz/layout/header.py
gcviz/layout/selection_bar.py
gcviz/layout/sites_selection.py
gcviz/views/agage_12box_emissions.py
gcviz/views/base_figures.py
gcviz/views/correlation_view.py
gcviz/views/data_tables.py
gcviz/views/example_view.py
gcviz/views/temporal_patterns.py
gcviz-0.2.0.dist-info/METADATA
gcviz-0.2.0.dist-info/WHEEL
gcviz-0.2.0.dist-info/licenses/LICENCE.txt
gcviz-0.2.0.dist-info/RECORD
