Metadata-Version: 2.3
Name: gcviz
Version: 0.2.0
Summary: Gorgeous and Captivating Visualization of air measurements data.
Project-URL: Homepage, https://gcviz.empa.ch
Project-URL: Bug Tracker, https://gitlab.com/empa503/atmospheric-measurements/gcviz/issues
Author-email: Constantin Lionel <lionel.constantin@empa.ch>
License-File: LICENCE.txt
Classifier: License :: OSI Approved :: MIT License
Classifier: Operating System :: OS Independent
Classifier: Programming Language :: Python :: 3
Requires-Python: >=3.12
Requires-Dist: dash
Requires-Dist: dash-bootstrap-components
Requires-Dist: h5netcdf
Requires-Dist: pandas
Requires-Dist: pybaselines
Requires-Dist: xarray
